askmydb/__init__.py
askmydb/askmydb.py
askmydb/llm/__init__.py
askmydb/llm/base.py
askmydb/llm/dummy.py
askmydb/llm/ollama_provider.py
askmydb/llm/openai_provider.py
askmydb/llm/sql_prompt.py
askmydb/schema/__init__.py
askmydb/schema/loader.py
askmydb/sql/__init__.py
askmydb/sql/executor.py
askmydb-0.1.6.dist-info/licenses/LICENSE
examples/run_dummy.py
examples/run_ollama_llm.py
examples/run_openrouter_llm.py
tests/test_ollama_provider.py
askmydb-0.1.6.dist-info/METADATA
askmydb-0.1.6.dist-info/WHEEL
askmydb-0.1.6.dist-info/top_level.txt
askmydb-0.1.6.dist-info/RECORD
