Metadata-Version: 2.4
Name: askmydb
Version: 0.1.6
Summary: A Python package for querying databases using natural language.
Home-page: https://github.com/Msalways/Ask-My-DB
Author: Shanthosh
Author-email: shanthubolt@gmail.com
License: MIT
Requires-Python: >=3.7
License-File: LICENSE
Requires-Dist: sqlalchemy
Provides-Extra: dev
Requires-Dist: black; extra == "dev"
Requires-Dist: pytest; extra == "dev"
Provides-Extra: openai
Requires-Dist: openai; extra == "openai"
Provides-Extra: ollama
Requires-Dist: ollama; extra == "ollama"
Provides-Extra: all
Requires-Dist: sqlalchemy; extra == "all"
Requires-Dist: black; extra == "all"
Requires-Dist: pytest; extra == "all"
Requires-Dist: openai; extra == "all"
Requires-Dist: ollama; extra == "all"
Dynamic: author-email
Dynamic: home-page
Dynamic: license-file
Dynamic: requires-python
